{
  "project_info": {
    "project_number": "761530514795",
    "firebase_url": "https://geolocalisation-14110.firebaseio.com",
    "project_id": "geolocalisation-14110",
    "storage_bucket": "geolocalisation-14110.appspot.com"
  },
  "client": [
    {
      "client_info": {
        "mobilesdk_app_id": "1:761530514795:android:7f4339e8791b3190d0602e",
        "android_client_info": {
          "package_name": "com.muhameddhouibi.geolocalisation"
        }
      },
      "oauth_client": [
        {
          "client_id": "761530514795-vgha7oc9oecjpetl29vftkli1i63pbl7.apps.googleusercontent.com",
          "client_type": 3
        }
      ],
      "api_key": [
        {
          "current_key": "AIzaSyD3rJFPL8xvWEjR-Txip57otRpj2p3jXBM"
        }
      ],
      "services": {
        "appinvite_service": {
          "other_platform_oauth_client": [
            {
              "client_id": "761530514795-vgha7oc9oecjpetl29vftkli1i63pbl7.apps.googleusercontent.com",
              "client_type": 3
            }
          ]
        }
      }
    }
  ],
  "configuration_version": "1"
}